kbeta_transformer2d/__init__.py
kbeta_transformer2d/data.py
kbeta_transformer2d/demo_heat2d.py
kbeta_transformer2d/io_utils.py
kbeta_transformer2d/model.py
kbeta_transformer2d/optim_factory.py
kbeta_transformer2d/plot_utils.py
kbeta_transformer2d/py.typed
kbeta_transformer2d/train.py
kbeta_transformer2d/utils.py
kbeta_transformer2d/configs/heat2d.yml
kbeta_transformer2d/configs/paper.yml
kbeta_transformer2d/configs/quick_test.yml
kbeta_transformer2d-1.0.0.dist-info/licenses/LICENSE
kbeta_transformer2d-1.0.0.dist-info/METADATA
kbeta_transformer2d-1.0.0.dist-info/WHEEL
kbeta_transformer2d-1.0.0.dist-info/top_level.txt
kbeta_transformer2d-1.0.0.dist-info/RECORD
