Metadata-Version: 2.4
Name: kbeta-transformer2d
Version: 1.0.0
Summary: 2-D Heat-Diffusion Transformer benchmark for Kourkoutas-β
Author: Stavros Kassinos
Project-URL: Homepage, https://github.com/sck-at-ucy/kbeta-transformer2d
Project-URL: Documentation, https://github.com/sck-at-ucy/kbeta-transformer2d
Project-URL: Repository, https://github.com/sck-at-ucy/kbeta-transformer2d
Classifier: Programming Language :: Python :: 3
Classifier: License :: OSI Approved :: MIT License
Classifier: Operating System :: MacOS :: MacOS X
Classifier: Intended Audience :: Science/Research
Classifier: Topic :: Scientific/Engineering :: Artificial Intelligence
Classifier: Topic :: Scientific/Engineering :: Physics
Requires-Python: >=3.9
License-File: LICENSE
Requires-Dist: numpy
Requires-Dist: pyyaml
Requires-Dist: mlx>=0.27.1
Requires-Dist: matplotlib>=3.7
Requires-Dist: seaborn>=0.13
Requires-Dist: pandas>=2.0
Requires-Dist: kbeta<2,>=1.0.0
Provides-Extra: dev
Requires-Dist: pytest; extra == "dev"
Requires-Dist: ruff; extra == "dev"
Requires-Dist: mypy; extra == "dev"
Provides-Extra: repro
Requires-Dist: mlx==0.26.3; extra == "repro"
Requires-Dist: kbeta==1.0.0; extra == "repro"
Requires-Dist: numpy; extra == "repro"
Requires-Dist: pyyaml; extra == "repro"
Requires-Dist: matplotlib>=3.7; extra == "repro"
Requires-Dist: seaborn>=0.13; extra == "repro"
Requires-Dist: pandas>=2.0; extra == "repro"
Requires-Dist: pytest; extra == "repro"
Requires-Dist: ruff; extra == "repro"
Requires-Dist: mypy; extra == "repro"
Dynamic: license-file
